llmspec-0.3.18.dist-info/METADATA
llmspec-0.3.18.dist-info/WHEEL
llmspec-0.3.18.dist-info/licenses/LICENSE
llmspec/__init__.py
llmspec/__version__.py
llmspec/llmspec.py
llmspec/mixins.py
llmspec/model_info.py
llmspec/py.typed
llmspec-0.3.18.dist-info/RECORD
