Metadata-Version: 2.1
Name: llmspec
Version: 0.3.18
Summary: LLM unified interface
Keywords: machine learning deep learning large language model
Author-Email: TensorChord <modelz@tensorchord.ai>
License: Apache-2.0
Classifier: Intended Audience :: Developers
Classifier: Topic :: Scientific/Engineering :: Artificial Intelligence
Requires-Python: >=3.8
Requires-Dist: msgspec>=0.18.4
